molo.core-11.3.2-py3.8-nspkg.pth
molo/core/__init__.py
molo/core/admin.py
molo/core/apps.py
molo/core/backends.py
molo/core/blocks.py
molo/core/constants.py
molo/core/context_processors.py
molo/core/cookiecutter.py
molo/core/decorators.py
molo/core/forms.py
molo/core/known_plugins.py
molo/core/middleware.py
molo/core/mixins.py
molo/core/models.py
molo/core/molo_wagtail_models.py
molo/core/page_utils.py
molo/core/processors.py
molo/core/tasks.py
molo/core/urls.py
molo/core/utils.py
molo/core/views.py
molo/core/wagtail_hooks.py
molo/core/api/__init__.py
molo/core/api/admin_views.py
molo/core/api/constants.py
molo/core/api/endpoints.py
molo/core/api/errors.py
molo/core/api/filters.py
molo/core/api/forms.py
molo/core/api/importers.py
molo/core/api/serializers.py
molo/core/api/urls.py
molo/core/api/tests/__init__.py
molo/core/api/tests/constants.py
molo/core/api/tests/test_forms.py
molo/core/api/tests/test_importers.py
molo/core/api/tests/test_views.py
molo/core/api/tests/utils.py
molo/core/cookiecutter/scaffold/cookiecutter.json
molo/core/cookiecutter/scaffold/{{cookiecutter.directory}}/.deploy.yaml
molo/core/cookiecutter/scaffold/{{cookiecutter.directory}}/.gitignore
molo/core/cookiecutter/scaffold/{{cookiecutter.directory}}/.travis.yml
molo/core/cookiecutter/scaffold/{{cookiecutter.directory}}/LICENSE
molo/core/cookiecutter/scaffold/{{cookiecutter.directory}}/MANIFEST.in
molo/core/cookiecutter/scaffold/{{cookiecutter.directory}}/README.rst
molo/core/cookiecutter/scaffold/{{cookiecutter.directory}}/VERSION
molo/core/cookiecutter/scaffold/{{cookiecutter.directory}}/manage.py
molo/core/cookiecutter/scaffold/{{cookiecutter.directory}}/requirements-dev.txt
molo/core/cookiecutter/scaffold/{{cookiecutter.directory}}/requirements.txt
molo/core/cookiecutter/scaffold/{{cookiecutter.directory}}/setup.cfg
molo/core/cookiecutter/scaffold/{{cookiecutter.directory}}/setup.py
molo/core/cookiecutter/scaffold/{{cookiecutter.directory}}/test_settings.py
molo.core-11.3.2.dist-info/LICENSE
molo.core-11.3.2.dist-info/METADATA
molo.core-11.3.2.dist-info/WHEEL
molo.core-11.3.2.dist-info/entry_points.txt
molo.core-11.3.2.dist-info/namespace_packages.txt
molo.core-11.3.2.dist-info/top_level.txt
molo.core-11.3.2.dist-info/RECORD
