Metadata-Version: 2.1
Name: molo.core
Version: 11.3.2
Summary: Molo is a set of tools for publishing mobi sites with a community focus.
Home-page: http://github.com/praekelt/molo
Author: Praekelt.org
Author-email: dev@praekelt.org
License: BSD
Keywords: praekelt,mobi,web,django
Platform: UNKNOWN
Classifier: Development Status :: 5 - Production/Stable
Classifier: Environment :: Web Environment
Classifier: Framework :: Django
Classifier: Intended Audience :: Developers
Classifier: License :: OSI Approved :: BSD License
Classifier: Programming Language :: Python
Classifier: Programming Language :: Python :: 3
Classifier: Programming Language :: Python :: 3.5
Classifier: Topic :: Internet :: WWW/HTTP
Classifier: Topic :: Internet :: WWW/HTTP :: WSGI :: Application
Requires-Dist: babel
Requires-Dist: beautifulsoup4 (<4.9,>=4.8)
Requires-Dist: cached-property
Requires-Dist: celery (==4.4.7)
Requires-Dist: cookiecutter (==1.0.0)
Requires-Dist: dj-database-url
Requires-Dist: Django (~=3.1.4)
Requires-Dist: django-cas-ng (==4.1.1)
Requires-Dist: django-el-pagination (==3.1.0)
Requires-Dist: django-extensions
Requires-Dist: django-admin-rangefilter (==0.8.1)
Requires-Dist: django-google-analytics-app (==5.0.1)
Requires-Dist: django-libsass
Requires-Dist: django-mptt (~=0.11.0)
Requires-Dist: djangorestframework (<4.0,>=3.11.1)
Requires-Dist: django-phonenumber-field (==1.3.0)
Requires-Dist: django-import-export (==2.3.0)
Requires-Dist: markdown (>=3.0.1)
Requires-Dist: mote-praekelt (~=0.3.0)
Requires-Dist: raven (~=6.10.0)
Requires-Dist: redis (==3.5.3)
Requires-Dist: requests
Requires-Dist: setuptools (>=18.5)
Requires-Dist: six (>=1.12.0)
Requires-Dist: ujson (==1.35)
Requires-Dist: unicodecsv (==0.14.1)
Requires-Dist: unicore.content
Requires-Dist: wagtail (==2.10.2)
Requires-Dist: wagtailmedia (~=0.7.0)
Requires-Dist: ImageHash (==3.4)
Requires-Dist: boto (==2.49.0)
Requires-Dist: django-storages (==1.7.1)
Requires-Dist: Unidecode (==0.04.16)
Requires-Dist: django-treebeard (==4.2.0)
Requires-Dist: django-prometheus
Requires-Dist: prometheus-client
Requires-Dist: django-enumfield (==2.0.2)
Requires-Dist: html2markdown
Requires-Dist: django-utils-six
